<?xml version="1.0" encoding="utf-8"?>
<!DOCTYPE hibernate-mapping PUBLIC "-//Hibernate/Hibernate Mapping DTD 3.0//EN"
"http://hibernate.sourceforge.net/hibernate-mapping-3.0.dtd">
<!-- 
    Mapping file autogenerated by MyEclipse Persistence Tools
-->
<hibernate-mapping>
    <class name="com.common.entity.VBusinreceivereport" table="v_businreceivereport" catalog="oa3">
			<id name="businId" type="java.lang.Integer">
                <column name="businId"/>
            </id>
            <property name="empId" type="java.lang.Integer">
                <column name="empId" />
            </property>
            <property name="billNo" type="java.lang.String">
                <column name="billNo" length="100" />
            </property>
            <property name="cusId" type="java.lang.Integer">
                <column name="cusId" />
            </property>
            <property name="cusName" type="java.lang.String">
                <column name="cusName" length="200" />
            </property>
            <property name="cusId2" type="java.lang.Integer">
                <column name="cusId2" />
            </property>
            <property name="cusName2" type="java.lang.String">
                <column name="cusName2" length="200" />
            </property>
            <property name="cdate" type="java.sql.Timestamp">
                <column name="cdate" length="0" />
            </property>
            <property name="cdate1" type="java.sql.Timestamp">
                <column name="cdate1" length="0" />
            </property>
            <property name="cdate2" type="java.sql.Timestamp">
                <column name="cdate2" length="0" />
            </property>
            <property name="cdate3" type="java.sql.Timestamp">
                <column name="cdate3" length="0" />
            </property>
            <property name="cdate4" type="java.sql.Timestamp">
                <column name="cdate4" length="0" />
            </property>
            <property name="cmoney" type="java.lang.Double">
                <column name="cmoney" />
            </property>
            <property name="receiveMoney1" type="java.lang.Double">
                <column name="receiveMoney1" />
            </property>
             <property name="receiveMoney2" type="java.lang.Double">
                <column name="receiveMoney2" />
            </property>
            <property name="receiveMoney3" type="java.lang.Double">
                <column name="receiveMoney3" />
            </property>
            <property name="receiveMoney4" type="java.lang.Double">
                <column name="receiveMoney4" />
            </property>
            <property name="receiveMoney" type="java.lang.Double">
                <column name="receiveMoney" />
            </property>
            <property name="cmoney2" type="java.lang.Double">
                <column name="cmoney2" />
            </property>
            <property name="empName" type="java.lang.String">
                <column name="empName" length="200" />
            </property>
            <property name="reim" type="java.lang.String">
                <column name="reim" length="200" />
            </property>
            <property name="inv" type="java.lang.String">
                <column name="inv" length="200" />
            </property>
            <property name="schedule_archive" type="java.lang.Short">
                <column name="schedule_archive" />
            </property>
            <property name="nodate5" type="java.lang.String">
                <column name="nodate5" length="200" />
            </property>
           <property name="nodate7" type="java.lang.String">
                <column name="nodate7" length="200" />
            </property> 
           <property name="remarks" type="java.lang.String">
                <column name="remarks" length="200" />
            </property> 
            <property name="remarks2" type="java.lang.String">
                <column name="remarks2" length="200" />
            </property>
             <property name="cnodate8" type="java.lang.String">
                <column name="cnodate8" length="100" />
            </property>
            <property name="money1" type="java.lang.Double">
                <column name="money1" />
            </property>
            <property name="money2" type="java.lang.Double">
                <column name="money2" />
            </property>
            <property name="money4" type="java.lang.Double">
                <column name="money4" />
            </property>
            <property name="payComplete" type="java.lang.Short">
                <column name="payComplete" />
            </property>
            <property name="lastDate2" type="java.sql.Timestamp">
                <column name="lastDate2" length="0" />
            </property>
            <property name="vatno" type="java.lang.String">
                <column name="vatno" length="100" />
            </property>
            <property name="description" type="java.lang.String">
                <column name="description" length="100" />
            </property>
            <property name="qtyoftruck" type="java.lang.String">
                <column name="qtyoftruck" length="100" />
            </property>
            <property name="qtyofdox" type="java.lang.String">
                <column name="qtyofdox" length="100" />
            </property>
            <property name="fty" type="java.lang.String">
                <column name="fty" length="100" />
            </property>
            <property name="arrivalPort" type="java.lang.String">
                <column name="arrivalPort" length="100" />
            </property>
           <property name="acNotice" type="java.lang.Short">
                <column name="acNotice" />
            </property>
            <property name="salerId" type="java.lang.Integer">
                <column name="salerId" />
            </property>
    </class>
</hibernate-mapping>
